dff_node_stats/__init__.py
dff_node_stats/api.py
dff_node_stats/collectors.py
dff_node_stats/stats.py
dff_node_stats/utils.py
dff_node_stats/savers/__init__.py
dff_node_stats/savers/clickhouse.py
dff_node_stats/savers/csv.py
dff_node_stats/savers/postgresql.py
dff_node_stats/savers/saver.py
dff_node_stats/widgets/__init__.py
dff_node_stats/widgets/jupyter.py
dff_node_stats/widgets/streamlit.py
dff_node_stats/widgets/visualizers.py
dff_node_stats/widgets/widget.py
examples/__init__.py
examples/collect_stats.py
examples/collect_stats_vscode_demo.py
examples/get_stats_by_api.py
examples/run_dashboard_for_stats.py
tests/__init__.py
tests/conftest.py
tests/test_api.py
tests/test_collectors.py
tests/test_dashboard.py
tests/test_savers.py
tests/test_visualizers.py
dff_node_stats-0.1.2.dist-info/LICENSE
dff_node_stats-0.1.2.dist-info/METADATA
dff_node_stats-0.1.2.dist-info/WHEEL
dff_node_stats-0.1.2.dist-info/top_level.txt
dff_node_stats-0.1.2.dist-info/RECORD
