Metadata-Version: 2.1
Name: dff-node-stats
Version: 0.1.2
Summary: Statistics collection extension for Dialog Flow Framework (https://github.com/deepmipt/dialog_flow_framework).
Home-page: https://github.com/kudep/dff-node-stats
Author: Denis Kuznetsov
Author-email: kuznetsov.den.p@gmail.com
Classifier: Programming Language :: Python :: 3
Classifier: License :: OSI Approved :: Apache Software License
Classifier: Operating System :: OS Independent
License-File: LICENSE
Requires-Dist: pandas (>=1.3.1)
Requires-Dist: df-engine (>=0.8.1)
Requires-Dist: tqdm (>=4.62.3)
Requires-Dist: pydantic (>=1.8.2)
Provides-Extra: all
Requires-Dist: infi.clickhouse-orm (==2.1.1) ; extra == 'all'
Requires-Dist: psycopg2 (>=2.9.2) ; extra == 'all'
Requires-Dist: SQLAlchemy (==1.4.27) ; extra == 'all'
Requires-Dist: fastapi (>=0.68.0) ; extra == 'all'
Requires-Dist: uvicorn (>=0.14.0) ; extra == 'all'
Requires-Dist: streamlit (>=1.1.0) ; extra == 'all'
Requires-Dist: graphviz (==0.17) ; extra == 'all'
Requires-Dist: ipywidgets (==7.6.5) ; extra == 'all'
Requires-Dist: traitlets (==5.1.1) ; extra == 'all'
Requires-Dist: plotly (>=5.5.0) ; extra == 'all'
Provides-Extra: api
Requires-Dist: fastapi (>=0.68.0) ; extra == 'api'
Requires-Dist: uvicorn (>=0.14.0) ; extra == 'api'
Provides-Extra: clickhouse
Requires-Dist: infi.clickhouse-orm (==2.1.1) ; extra == 'clickhouse'
Provides-Extra: dev
Requires-Dist: infi.clickhouse-orm (==2.1.1) ; extra == 'dev'
Requires-Dist: psycopg2 (>=2.9.2) ; extra == 'dev'
Requires-Dist: SQLAlchemy (==1.4.27) ; extra == 'dev'
Requires-Dist: fastapi (>=0.68.0) ; extra == 'dev'
Requires-Dist: uvicorn (>=0.14.0) ; extra == 'dev'
Requires-Dist: streamlit (>=1.1.0) ; extra == 'dev'
Requires-Dist: graphviz (==0.17) ; extra == 'dev'
Requires-Dist: ipywidgets (==7.6.5) ; extra == 'dev'
Requires-Dist: traitlets (==5.1.1) ; extra == 'dev'
Requires-Dist: plotly (>=5.5.0) ; extra == 'dev'
Provides-Extra: jupyter
Requires-Dist: ipywidgets (==7.6.5) ; extra == 'jupyter'
Requires-Dist: traitlets (==5.1.1) ; extra == 'jupyter'
Requires-Dist: graphviz (>=0.17) ; extra == 'jupyter'
Requires-Dist: plotly (>=5.5.0) ; extra == 'jupyter'
Provides-Extra: pg
Requires-Dist: psycopg2 (>=2.9.2) ; extra == 'pg'
Requires-Dist: SQLAlchemy (==1.4.27) ; extra == 'pg'
Provides-Extra: streamlit
Requires-Dist: streamlit (>=1.1.0) ; extra == 'streamlit'
Requires-Dist: graphviz (>=0.17) ; extra == 'streamlit'
Requires-Dist: plotly (>=5.5.0) ; extra == 'streamlit'
